autofns/__init__.py
autofns-0.1.7.dist-info/LICENSE
autofns-0.1.7.dist-info/METADATA
autofns-0.1.7.dist-info/WHEEL
autofns-0.1.7.dist-info/RECORD
