Metadata-Version: 2.1
Name: autofns
Version: 0.1.7
Summary: AutoFNS is a utility for automatically calling functions when interacting with the OpenAI Completions.
Home-page: https://github.com/rhymiz/autofns
License: MIT
Keywords: ai,openai,gpt-3,gpt-4,functions,chat completions,utility,autofns
Author: Lemuel Boyce
Author-email: lemuelboyce@gmail.com
Requires-Python: >=3.10,<4.0
Classifier: Development Status :: 3 - Alpha
Classifier: Intended Audience :: Developers
Classifier: License :: OSI Approved :: MIT License
Classifier: Operating System :: OS Independent
Classifier: Programming Language :: Python :: 3
Classifier: Programming Language :: Python :: 3.10
Classifier: Programming Language :: Python :: 3.11
Classifier: Programming Language :: Python :: 3.12
Classifier: Programming Language :: Python :: 3 :: Only
Classifier: Topic :: Software Development :: Libraries :: Python Modules
Classifier: Topic :: Text Processing :: Linguistic
Classifier: Typing :: Typed
Requires-Dist: openai (>=1.6.1,<2.0.0)
Project-URL: Repository, https://github.com/rhymiz/autofns
